dbnd_airflow_operator/__init__.py
dbnd_airflow_operator-0.49.6.dist-info/LICENSE
dbnd_airflow_operator-0.49.6.dist-info/METADATA
dbnd_airflow_operator-0.49.6.dist-info/WHEEL
dbnd_airflow_operator-0.49.6.dist-info/top_level.txt
dbnd_airflow_operator-0.49.6.dist-info/RECORD
